{
  "folderName": "书签栏",
  "lastSyncTime": "2026-04-29T07:21:15.453Z",
  "bookmarks": [
    {
      "title": "Google",
      "url": "https://www.google.com",
      "iconFileName": null,
      "urlStatus": "unknown",
      "lastVisited": null,
      "isInvalid": false,
      "syncStatus": "completed",
      "lastSyncTime": null
    },
    {
      "title": "GitHub",
      "url": "https://www.github.com",
      "iconFileName": null,
      "urlStatus": "unknown",
      "lastVisited": null,
      "isInvalid": false,
      "syncStatus": "completed",
      "lastSyncTime": null
    }
  ],
  "syncInfo": {
    "syncId": "sync_1777447275449",
    "startTime": "2026-04-29T07:21:15.449Z",
    "endTime": "2026-04-29T07:21:15.453Z",
    "totalBookmarks": 2,
    "completedBookmarks": 2,
    "failedBookmarks": 0
  }
}